oauth2link/__init__.py
oauth2link/types.py
oauth2link/utils.py
oauth2link/callback/__init__.py
oauth2link/callback/callback.py
oauth2link/platform/__init__.py
oauth2link/platform/github_platform.py
oauth2link/platform/platform.py
oauth2link/platform/weibo_platform.py
oauth2link-0.0.4.dist-info/LICENSE
oauth2link-0.0.4.dist-info/METADATA
oauth2link-0.0.4.dist-info/WHEEL
oauth2link-0.0.4.dist-info/top_level.txt
oauth2link-0.0.4.dist-info/RECORD
