Metadata-Version: 2.1
Name: oauth2link
Version: 0.0.4
Summary: oauth2 link
Home-page: https://github.com/Bean-jun/oauth2link
Author: Bean-jun
Author-email: 1342104001@qq.com
License: MIT License
Platform: UNKNOWN
Classifier: License :: OSI Approved :: MIT License
Classifier: Programming Language :: Python :: 3.9
Classifier: Programming Language :: Python :: 3.10
License-File: LICENSE
Requires-Dist: Flask >=2.3.2
Requires-Dist: Flask-SQLAlchemy >=3.0.5
Requires-Dist: requests >=2.31.0
